robobopy/Robobo.py
robobopy/State.py
robobopy/__init__.py
robobopy/remotelib.py
robobopy/processors/AbstractProcessor.py
robobopy/processors/PTProcessor.py
robobopy/processors/RobProcessor.py
robobopy/processors/SmartphoneProcessor.py
robobopy/processors/SoundProcessor.py
robobopy/processors/SpeechProcessor.py
robobopy/processors/VisionProcessor.py
robobopy/processors/__init__.py
robobopy/utils/Acceleration.py
robobopy/utils/Blob.py
robobopy/utils/BlobColor.py
robobopy/utils/Color.py
robobopy/utils/ConnectionState.py
robobopy/utils/DetectedObject.py
robobopy/utils/Emotions.py
robobopy/utils/Face.py
robobopy/utils/IR.py
robobopy/utils/LED.py
robobopy/utils/Lanes.py
robobopy/utils/Lines.py
robobopy/utils/Message.py
robobopy/utils/Note.py
robobopy/utils/Orientation.py
robobopy/utils/QRCode.py
robobopy/utils/Sounds.py
robobopy/utils/Speech.py
robobopy/utils/StatusFrequency.py
robobopy/utils/Tag.py
robobopy/utils/Tap.py
robobopy/utils/Wheels.py
robobopy/utils/__init__.py
robobopy-1.5.0.dist-info/LICENSE
robobopy-1.5.0.dist-info/METADATA
robobopy-1.5.0.dist-info/WHEEL
robobopy-1.5.0.dist-info/top_level.txt
robobopy-1.5.0.dist-info/RECORD
